{
	"swiper":{
		"1":"images/1489380460128.jpg",
		"2":"images/1489468346157.jpg",
		"3":"images/1489972261437.jpg",
		"4":"images/1490601963948.jpg",
		"5":"images/1490602108065.jpg"
	},
	"kind":{
		"img1":"images/1481507929526.jpg",
		"img2":"images/1481507940126.jpg",
		"img3":"images/1489052167830.jpg",
		"img4":"images/1489052567228.jpg",
		"img5":"images/1489052225375.jpg",
		"img6":"images/1488875371178.jpg",
		"img7":"images/1488975795371.jpg",
		"img8":"images/1481507997524.jpg"
	},
	"supermarket1":{
		"img1":"images/1488980676306.jpg",
		"img2":"images/1488980686351.jpg"
	},
	"supermarket2":{
		"img3":"images/1488981014917.jpg",
		"img4":"images/1488981026898.jpg",
		"img5":"images/121.jpg"
	},
	"tuijian":{
		"1":{
			"img":"images/1.jpg",
			"title":"公牛 新国标系列插座GN-S1220",
			"price":"￥58.00"
		},
		"2":{
			"img":"images/2.jpg",
			"title":"萌萌奶牛杯情侣对杯(2个)",
			"price":"￥40.00"
		},
		"3":{
			"img":"images/3.jpg",
			"title":"龙的真空保鲜盒 LD-FH15A",
			"price":"￥95.00"
		},
		"4":{
			"img":"images/4.jpg",
			"title":"乐扣乐扣 大容量收纳盒(以实物为准)",
			"price":"￥100.00"
		},
		"5":{
			"img":"images/5.jpg",
			"title":"伯尔尼斯优质不锈钢汤勺(25cm)",
			"price":"￥20.00"
		},
		"6":{
			"img":"images/6.jpg",
			"title":"伯尔尼斯 密封罐三件套(3个)",
			"price":"￥89.00"
		},
		"7":{
			"img":"images/7.jpg",
			"title":"伯尔尼斯 优质不锈钢汤漏(25cm)",
			"price":"￥20.00"
		},
		"8":{
			"img":"images/8.jpg",
			"title":"伯尔尼斯 西餐具四件套(高级不锈钢)",
			"price":"￥103.00"
		},
		"9":{
			"img":"images/9.jpg",
			"title":"大润窑 2头日式时尚蓝钻罐瓶搭配(2个)",
			"price":"￥85.00"
		},
		"10":{
			"img":"images/10.jpg",
			"title":"大润窑7头青春茶具(7)",
			"price":"￥99.00"
		},
		"11":{
			"img":"images/11.jpg",
			"title":"大润窑 汝窑8头茶具",
			"price":"￥199.00"
		},
		"12":{
			"img":"images/12.jpg",
			"title":"大润窑 汝窑10头茶具",
			"price":"￥110.00"
		}
	}
}









